fasta_lib/__init__.py
fasta_lib-0.0.2.dist-info/LICENSE.txt
fasta_lib-0.0.2.dist-info/METADATA
fasta_lib-0.0.2.dist-info/WHEEL
fasta_lib-0.0.2.dist-info/top_level.txt
fasta_lib-0.0.2.dist-info/RECORD
