Metadata-Version: 2.1
Name: fasta-lib
Version: 0.0.2
Summary: tool to parse fasta files
Home-page: 
Author: Claire Hsieh
Author-email: clhsieh@ucdavis.edu
License: MIT
Keywords: fasta
Classifier: Development Status :: 5 - Production/Stable
Classifier: Intended Audience :: Education
Classifier: Operating System :: Microsoft :: Windows :: Windows 10
Classifier: License :: OSI Approved :: MIT License
Classifier: Programming Language :: Python :: 3
License-File: LICENSE.txt
